LICENSE.rst
README.md
setup.cfg
setup.py
KAVICA.egg-info/PKG-INFO
KAVICA.egg-info/SOURCES.txt
KAVICA.egg-info/dependency_links.txt
KAVICA.egg-info/not-zip-safe
KAVICA.egg-info/requires.txt
KAVICA.egg-info/top_level.txt
kavica/__init__.py
kavica/distance_measure.py
kavica/graph_data_structur.py
kavica/mutual_knn.py
kavica/_hpc/__init__.py
kavica/_hpc/feature_engineering.py
kavica/_hpc/util.py
kavica/cluster_inference_system/OCA.py
kavica/cluster_inference_system/__init__.py
kavica/cluster_inference_system/_oca_empirical_study.py
kavica/cluster_inference_system/bilinear_transformation.py
kavica/cluster_inference_system/polygon_cage.py
kavica/cluster_inference_system/som.py
kavica/cluster_inference_system/somis.py
kavica/cluster_inference_system/space_curvature_map.py
kavica/factor_analysis/__init__.py
kavica/factor_analysis/factor_rotation.py
kavica/factor_analysis/rotation_function.py
kavica/feature_selection/__init__.py
kavica/feature_selection/base.py
kavica/feature_selection/feature_analysis.py
kavica/feature_selection/spectral_methods.py
kavica/imputation/__init__.py
kavica/imputation/base.py
kavica/imputation/mice.py
kavica/parser/__init__.py
kavica/parser/csv2prv.py
kavica/parser/parser_generate_cython.py
kavica/parser/prv2csv.py
kavica/parser/setup.py
kavica/parser/version.py
kavica/resampling/__init__.py
kavica/resampling/bootstrapper.py
kavica/utils/__init__.py
kavica/utils/_bcolors.py
kavica/utils/_dataset.py
kavica/utils/_generate_dataset.py
kavica/utils/_models.py
kavica/utils/_plots.py
kavica/utils/_progress_bar.py
kavica/utils/_prv_utility.py
kavica/utils/_util.py
kavica/utils/exploratory_analysis.py