Metadata-Version: 2.1
Name: KAVICA
Version: 1.3.4
Summary: KAVICA: Powerful Python Cluster Analysis and Inference Toolkit
Home-page: https://github.com/kavehmahdavi/kavica
Author: Kaveh Mahdavi
Author-email: kavehmahdavi74@yahoo.com
License: UNKNOWN
Project-URL: Documentation, http://kavehmahdavi.github.io/kavica/
Project-URL: Forum, http://kavehmahdavi.github.io/
Project-URL: Repository, https://github.com/kavehmahdavi/kavica
Project-URL: Issues, https://github.com/kavehmahdavi/kavica/issues
Project-URL: Author, http://kavehmahdavi.github.io/
Keywords: Cluster Inference System,Feature Selection,Factor Analysis,Parser,Clustering,Unsupervised,Self-organizing map,Organization Component Analysis,Feature Space Curvature Map,Multiline Transformation
Platform: UNKNOWN
Classifier: Programming Language :: Python :: 3
Classifier: Programming Language :: Python :: 3.4
Classifier: Programming Language :: Python :: 3.5
Classifier: Programming Language :: Python :: 3.6
Classifier: Programming Language :: Python :: 3.7
Classifier: Programming Language :: Python :: Implementation :: CPython
Classifier: License :: OSI Approved :: BSD License
Classifier: Operating System :: OS Independent
Classifier: Development Status :: 4 - Beta
Classifier: Intended Audience :: Developers
Classifier: Intended Audience :: Science/Research
Classifier: Topic :: Scientific/Engineering 
Classifier: Natural Language :: English
Requires-Python: >=3
License-File: LICENSE.rst
